LICENSE
MANIFEST.in
README.rst
setup.py
codingsoho_plugin.egg-info/PKG-INFO
codingsoho_plugin.egg-info/SOURCES.txt
codingsoho_plugin.egg-info/dependency_links.txt
codingsoho_plugin.egg-info/top_level.txt
docs/blank.txt
plugin/__init__.py
plugin/admin.py
plugin/apps.py
plugin/fields.py
plugin/forms.py
plugin/mixins.py
plugin/models.py
plugin/tests.py
plugin/utils.py
plugin/utils2.py
plugin/var.py
plugin/views.py
plugin/zips.py
plugin/migrations/__init__.py
plugin/templates/permission_alert.html
plugin/templates/admin/app_list.html
plugin/templates/admin/index.html
plugin/templates/dashboard/table_transposition_display_content.html
plugin/templates/dashboard/table_transposition_edit_formset.html
plugin/templates/default/create.html
plugin/templates/default/delete.html
plugin/templates/default/detail.html
plugin/templates/default/list.html
plugin/templates/default/update.html
plugin/templates/default/update_imageset.html
plugin/templates/includes/detail_panel.html
plugin/templates/includes/list_content.html
plugin/templates/includes/pagination.html
plugin/templates/inlines/list_panel.html
plugin/templates/plugin/default/base.html
plugin/templates/widgets/clearable_file_input.html
plugin/templatetags/__init__.py
plugin/templatetags/myform.py